{"hash":"9aa6fc4199609a4def2827be26b3f097c6fcb218","data":{"note":{"id":"cf6ef3da185f104238e25f583112060e","title":"Eniig Enterprise IMPL0001452 - Udfordringer med beskeder ud til Caller","year":2018,"content":"<p>Fra LP:\n<a href=\"https://app.liquidplanner.com/space/143625/my_work/panel/40673033\" target=\"_blank\" rel=\"nofollow noopener noreferrer\">https://app.liquidplanner.com/space/143625/my_work/panel/40673033</a></p>\n<p>Gemt i Business Rule: <code>Eniig-IfAssigneeBlankOnComment</code></p>\n<p>Update set: Eniig-1542</p>\n<p>Jacob:\nJeg er nødt til, at få en udvikler til, at lave den del, som evaluerer om incidentet kommenteres af en ITIL bruger, og assigned to er tom, for så, at sætte assigned to til den, som har opdateret incidentet via additional comments.</p>\n<p>Number: IMPL0001452\nOpened by: Thomas Gammelgaard Madsen</p>\n<p>Description: Vi har for ikke længe siden haft lignende sager, hvor svaret ikke kommer ud til caller, fordi der skrives til caller fra visitator-køen inden sagen tildeles en ITIL-person (assigned to). Denne er dog lidt anderledes: INC0032120</p>\n<p>Jeg fik et kald at en sag hastede, så jeg tog sagen over til mig, da visitator var fraværende. Jeg begynder på sagen og skriver i additional comments, hvad jeg har foretaget. I mellemtiden er visitator kommet retur og har åbenbart ikke opdateret sin visning, så sagen er stadig synlig i visitator-køen, så vedkommende (MSD i dette tilfælde) ændrer 'Assigned to' til ham selv, imens jeg sidder og arbejder i sagen. Da jeg er færdig og klikker på 'Update', får jeg en melding om, at sagen er blevet ændret imens jeg har arbejdet på den, men at ændringer i additional comments og worknotes ikke forsvinder ved, at jeg gemmer, så jeg siger OK og ændrer 'Assigned to' tilbage til mig selv. Jeg kan så se, at der ikke bliver sendt noget ud til caller. Det er et problem. Jeg kan ikke forstå, hvorfor setuppet skal være sådan. Vil det sige, at hvis jeg f.eks. går ind i en sag, hvor jeg ikke er personen i 'Assigned to' og skriver i Additional comments, så kommer det ikke ud til Caller og hvis ja, hvorfor gør det ikke det? Jeg kan forstå, at det ikke kommer ud, hvis assigned to er blank, men det burde være muligt at svaret kommer ud til caller, hvis assigned to er en anden end den, der skriver i assigned to.</p>\n<h3 id=\"ny-tekst-fra-deres-eniigs-system\"><a href=\"#ny-tekst-fra-deres-eniigs-system\" aria-hidden=\"true\"><span class=\"icon icon-link\"></span></a>Ny tekst fra deres Eniigs system</h3>\n<blockquote>\n<p>Vi ønsker, at hvis en sagsbehandler/ITIL-worker skriver i Additional comments på en incident, hvor Assigned to ikke er udfyldt, så skal Assigned to automatisk udfyldes til den sagsbehandler, som skriver i Additional Comments.</p>\n</blockquote>\n<p>Fra Jabob:</p>\n<blockquote>\n<p>Jeg havde allerede lavet en business rule til det:</p>\n</blockquote>\n<p><a href=\"https://eniigdev.service-now.com/nav_to.do?uri=sys_script.do?sys_id=2c2818d0db495b00039480e239961943\" target=\"_blank\" rel=\"nofollow noopener noreferrer\">https://eniigdev.service-now.com/nav_to.do?uri=sys_script.do?sys_id=2c2818d0db495b00039480e239961943</a></p>\n<h3 id=\"test\"><a href=\"#test\" aria-hidden=\"true\"><span class=\"icon icon-link\"></span></a>Test</h3>\n<p>INC0045333</p>\n<p>INC0044954</p>\n"}},"context":{}}